setup.py
src/dt_modeling/__init__.py
src/dt_modeling/dynamics/__init__.py
src/dt_modeling/dynamics/dynamics_delay.py
src/dt_modeling/dynamics/generic_kinematics.py
src/dt_modeling/dynamics/platform_dynamics.py
src/dt_modeling/dynamics/pwm_dynamics.py
src/dt_modeling/dynamics/types.py
src/dt_modeling/electronics/PWM.py
src/dt_modeling/electronics/__init__.py
src/dt_modeling/kinematics/__init__.py
src/dt_modeling/kinematics/forward.py
src/dt_modeling/kinematics/inverse.py
src/dt_modeling/kinematics/utils.py
src/dt_modeling/odometry/__init__.py
src/dt_modeling/odometry/types.py
src/dt_modeling/odometry/velocity_odometer.py
src/lib_dt_modeling.egg-info/PKG-INFO
src/lib_dt_modeling.egg-info/SOURCES.txt
src/lib_dt_modeling.egg-info/dependency_links.txt
src/lib_dt_modeling.egg-info/requires.txt
src/lib_dt_modeling.egg-info/top_level.txt