Metadata-Version: 2.1
Name: lib-dt-modeling
Version: 0.0.7
Home-page: http://github.com/duckietown/lib-dt-modeling
Author: Andrea F. Daniele
Author-email: afdaniele@duckietown.com
Requires-Dist: numpy<=1.21.5
Requires-Dist: transformations~=2021.6.6
